yourmt3/__init__.py
yourmt3/config/config.py
yourmt3/config/data_presets.py
yourmt3/config/task.py
yourmt3/config/vocabulary.py
yourmt3/model/conformer_helper.py
yourmt3/model/conformer_mod.py
yourmt3/model/conv_block.py
yourmt3/model/ff_layer.py
yourmt3/model/init_train.py
yourmt3/model/lm_head.py
yourmt3/model/lr_scheduler.py
yourmt3/model/ops.py
yourmt3/model/optimizers.py
yourmt3/model/perceiver_helper.py
yourmt3/model/perceiver_mod.py
yourmt3/model/pitchshift_layer.py
yourmt3/model/positional_encoding.py
yourmt3/model/projection_layer.py
yourmt3/model/spectrogram.py
yourmt3/model/t5mod.py
yourmt3/model/t5mod_helper.py
yourmt3/model/ymt3.py
yourmt3/model/RoPE/RoPE.py
yourmt3/utils/README.md
yourmt3/utils/audio.py
yourmt3/utils/augment.py
yourmt3/utils/data_modules.py
yourmt3/utils/datasets_eval.py
yourmt3/utils/datasets_helper.py
yourmt3/utils/datasets_train.py
yourmt3/utils/event2note.py
yourmt3/utils/event_codec.py
yourmt3/utils/metrics.py
yourmt3/utils/metrics_helper.py
yourmt3/utils/midi.py
yourmt3/utils/note2event.py
yourmt3/utils/note_event_dataclasses.py
yourmt3/utils/task_manager.py
yourmt3/utils/tokenizer.py
yourmt3/utils/utils.py
yourmt3-0.1.4.dist-info/METADATA
yourmt3-0.1.4.dist-info/WHEEL
yourmt3-0.1.4.dist-info/RECORD
