Metadata-Version: 2.4
Name: yourmt3
Version: 0.1.4
Summary: Music Transcription
Author-email: dummyjenil <dummyjenil@gmail.com>
Requires-Dist: einops
Requires-Dist: lightning
Requires-Dist: mido
Requires-Dist: mir-eval
Requires-Dist: scikit-learn
Requires-Dist: torchaudio
Requires-Dist: transformers==4.45.1
